README.md
setup.py
Complex_API/__init__.py
Complex_API/complex_api.py
Complex_API.egg-info/PKG-INFO
Complex_API.egg-info/SOURCES.txt
Complex_API.egg-info/dependency_links.txt
Complex_API.egg-info/entry_points.txt
Complex_API.egg-info/requires.txt
Complex_API.egg-info/top_level.txt