Metadata-Version: 2.1
Name: Complex-API
Version: 0.0.4
Summary: It makes it easier to use the API I have built/working on
Home-page: https://github.com/JagTheFriend/Complex-API
Author: JagTheFriend
Author-email: jagthefriend12@gmail.com
License: MIT
Platform: UNKNOWN
Classifier: License :: OSI Approved :: MIT License
Classifier: Programming Language :: Python :: 3.7
Classifier: Programming Language :: Python :: 3.8
